enhlib/LICENSE
enhlib/__init__.py
enhlib/collections.py
enhlib/contextlib.py
enhlib/csv.py
enhlib/datetime.py
enhlib/functools.py
enhlib/itertools.py
enhlib/misc.py
enhlib/random.py
enhlib/text.py
enhlib/types.py
enhlib/stdlib/__init__.py
enhlib/test/__init__.py
enhlib/test/__main__.py
enhlib/test/test_enhlib.py
enhlib-0.0.12.dist-info/METADATA
enhlib-0.0.12.dist-info/WHEEL
enhlib-0.0.12.dist-info/top_level.txt
enhlib-0.0.12.dist-info/RECORD
